fast_trade/__init__.py
fast_trade/build_data_frame.py
fast_trade/build_summary.py
fast_trade/calculate_perc_missing.py
fast_trade/cli.py
fast_trade/cli_helpers.py
fast_trade/evaluate.py
fast_trade/finta.py
fast_trade/run_analysis.py
fast_trade/run_backtest.py
fast_trade/transformers_map.py
fast_trade/utils.py
fast_trade/validate_backtest.py
fast_trade/archive/__init__.py
fast_trade/archive/binance_api.py
fast_trade/archive/cli.py
fast_trade/archive/coinbase_api.py
fast_trade/archive/db_helpers.py
fast_trade/archive/update_archive.py
fast_trade/archive/update_kline.py
fast_trade-1.0.3.dist-info/licenses/LICENSE
fast_trade-1.0.3.dist-info/METADATA
fast_trade-1.0.3.dist-info/WHEEL
fast_trade-1.0.3.dist-info/entry_points.txt
fast_trade-1.0.3.dist-info/top_level.txt
fast_trade-1.0.3.dist-info/RECORD
