Metadata-Version: 2.4
Name: fast-trade
Version: 1.0.3
Summary: Low code backtesting library utilizing pandas and technical analysis indicators
Author-email: Jed Meier <fast_trade@jedm.dev>
License: GNU AGPLv3
Project-URL: Homepage, https://github.com/jrmeier/fast-trade
Project-URL: Repository, https://github.com/jrmeier/fast-trade
Keywords: backtesting,currency,ta,pandas,finance,numpy,analysis,technical analysis
Classifier: Intended Audience :: Financial and Insurance Industry
Classifier: Programming Language :: Python :: 3.8
Classifier: Programming Language :: Python :: 3.9
Classifier: Programming Language :: Python :: 3.10
Classifier: Programming Language :: Python :: 3.11
Classifier: Topic :: Scientific/Engineering :: Mathematics
Classifier: Topic :: Software Development :: Libraries
Classifier: Intended Audience :: Developers
Classifier: License :: OSI Approved :: GNU Affero General Public License v3 or later (AGPLv3+)
Classifier: Operating System :: OS Independent
Classifier: Natural Language :: English
Requires-Python: >=3.8
License-File: LICENSE
Requires-Dist: pandas>=2.0.0
Requires-Dist: matplotlib>=3.7.0
Requires-Dist: requests>=2.31.0
Requires-Dist: numpy>=1.24.0
Dynamic: license-file
